TCGAdnloader/__init__.py
TCGAdnloader/convertor.py
TCGAdnloader/downloader.py
TCGAdnloader/outformat.py
TCGAdnloader/setting.py
TCGAdnloader/test.py
TCGAdnloader/data/PAM50.txt
TCGAdnloader/data/gencode.v22.annotation.gene.probeMap
TCGAdnloader-0.1.5.data/scripts/tcgaDnloader
TCGAdnloader-0.1.5.dist-info/LICENSE
TCGAdnloader-0.1.5.dist-info/METADATA
TCGAdnloader-0.1.5.dist-info/WHEEL
TCGAdnloader-0.1.5.dist-info/top_level.txt
TCGAdnloader-0.1.5.dist-info/RECORD
