Metadata-Version: 2.1
Name: TCGAdnloader
Version: 0.1.5
Summary: 
